LICENSE
MANIFEST.in
README.rst
setup.py
save/__init__.py
save.egg-info/PKG-INFO
save.egg-info/SOURCES.txt
save.egg-info/dependency_links.txt
save.egg-info/not-zip-safe
save.egg-info/top_level.txt