Metadata-Version: 1.1
Name: save
Version: 0.1
Summary: A very simple module to safely save data to files in python
Home-page: https://github.com/ndrbrt/save.py
Author: Andrea Bertoloni
Author-email: contact@andreabertoloni.com
License: MIT
Keywords: save data file path system
Platform: UNKNOWN
Classifier: Intended Audience :: Developers
Classifier: License :: OSI Approved :: MIT License
Classifier: Programming Language :: Python :: 2.7
Classifier: Topic :: System :: Filesystems
